mistral_image_gen/__init__.py
mistral_image_gen/image_generator.py
mistral_image_gen-0.1.0.dist-info/LICENSE
mistral_image_gen-0.1.0.dist-info/METADATA
mistral_image_gen-0.1.0.dist-info/WHEEL
mistral_image_gen-0.1.0.dist-info/top_level.txt
mistral_image_gen-0.1.0.dist-info/RECORD
