Metadata-Version: 2.1
Name: mistral-image-gen
Version: 0.1.0
Summary: A Python library for generating images using Mistral AI API
Home-page: https://github.com/yourusername/mistral-image-gen
Author: Your Name
Author-email: your.email@example.com
Classifier: Programming Language :: Python :: 3
Classifier: License :: OSI Approved :: MIT License
Classifier: Operating System :: OS Independent
Requires-Python: >=3.6
License-File: LICENSE
Requires-Dist: requests>=2.31.0
